murloc/__init__.py
murloc/murloc.py
murloc-0.1.1.dist-info/LICENSE
murloc-0.1.1.dist-info/METADATA
murloc-0.1.1.dist-info/WHEEL
murloc-0.1.1.dist-info/top_level.txt
murloc-0.1.1.dist-info/RECORD
