Metadata-Version: 2.1
Name: murloc
Version: 0.1.1
Summary: Extensible API server
Home-page: 
Author: Chris Varga
Author-email: 
Keywords: extensible api server
Classifier: Programming Language :: Python
Classifier: License :: OSI Approved :: MIT License
Classifier: Operating System :: OS Independent
License-File: LICENSE
Requires-Dist: uvicorn
Requires-Dist: hdb
